gnn_exp/__init__.py
gnn_exp/gnn_visualizer.py
gnn_exp/graph_editor.py
gnn_exp/graph_visualizer.py
gnn_exp/static/dual_views/index.css
gnn_exp/static/dual_views/index.js
gnn_exp/static/gnn_visualizer/index.css
gnn_exp/static/gnn_visualizer/index.js
gnn_exp/static/graph_editor/index.css
gnn_exp/static/graph_editor/index.js
gnn_exp/utils/__init__.py
gnn_exp/utils/data_loader.py
gnn_exp/utils/subgraph_sampling.py
gnn_exp-0.1.0.dist-info/licenses/LICENSE
gnn_exp-0.1.0.dist-info/METADATA
gnn_exp-0.1.0.dist-info/WHEEL
gnn_exp-0.1.0.dist-info/top_level.txt
gnn_exp-0.1.0.dist-info/RECORD
