Metadata-Version: 2.4
Name: gnn-exp
Version: 0.1.0
Summary: Visual exploration and explanation of Graph Neural Networks in computational notebooks
Author-email: Yilin Lu <lu000661@umn.edu>, Qianwen Wang <qianwen@umn.edu>
License: MIT
Project-URL: Homepage, https://github.com/HarryLuUMN/gnn-vis-widgets
Project-URL: Repository, https://github.com/HarryLuUMN/gnn-vis-widgets
Requires-Python: >=3.8
License-File: LICENSE
Requires-Dist: anywidget>=0.9.0
Dynamic: license-file
